nameisok/__init__.py
nameisok/_globals.py
nameisok/_result.py
nameisok/c_check.py
nameisok/cache.py
nameisok/cli.py
nameisok/core.py
nameisok/similar.py
nameisok/types_.py
nameisok-0.1.8.dist-info/METADATA
nameisok-0.1.8.dist-info/WHEEL
nameisok-0.1.8.dist-info/entry_points.txt
nameisok-0.1.8.dist-info/top_level.txt
nameisok-0.1.8.dist-info/RECORD
