Metadata-Version: 2.1
Name: nameisok
Version: 0.1.8
Summary: A utility package for checking if a package name is available on PyPI.
Author-email: Sermet Pekin <Sermet.Pekin@gmail.com>
License: MIT
Project-URL: repository, https://github.com/SermetPekin/nameisok
Project-URL: documentation, https://github.com/SermetPekin/nameisok#readme
Project-URL: issue_tracker, https://github.com/SermetPekin/nameisok/issues
Keywords: pypi,package availability,name checker,available,utility
Requires-Python: >=3.10
Requires-Dist: click>=8.1.7
Requires-Dist: fuzzywuzzy>=0.18.0
Requires-Dist: pytest>=8.3.3
Requires-Dist: python-levenshtein>=0.26.1
Requires-Dist: requests>=2.32.3
